{
  "name": "2016 Rio Open presented by Claro hdtv, Qualification ATP (Men's Singles)",
  "country": "Brazil",
  "gender": "male",
  "location": "Rio de Janeiro",
  "surface": "Clay",
  "events": [
    {
      "players": [
        {
          "is_winner": false,
          "set_games": [
            "6",
            "2",
            "1"
          ],
          "name": "Blaz Rola",
          "country": "SI"
        },
        {
          "is_winner": true,
          "set_games": [
            "3",
            "6",
            "6"
          ],
          "name": "Facundo Arguello",
          "country": "AR"
        }
      ],
      "duration": "02:10:27",
      "round": "Round of 16",
      "date": "2016-02-13"
    },
    {
      "players": [
        {
          "is_winner": false,
          "set_games": [
            "3",
            "2"
          ],
          "name": "Carlos Eduardo Severino",
          "country": "BR"
        },
        {
          "is_winner": true,
          "set_games": [
            "6",
            "6"
          ],
          "name": "Gastao Elias",
          "country": "PT"
        }
      ],
      "duration": "01:23:58",
      "round": "Round of 16",
      "date": "2016-02-13"
    },
    {
      "players": [
        {
          "is_winner": true,
          "set_games": [
            "6",
            "2",
            "6"
          ],
          "name": "Facundo Bagnis",
          "country": "AR"
        },
        {
          "is_winner": false,
          "set_games": [
            "3",
            "6",
            "4"
          ],
          "name": "Maximo Gonzalez",
          "country": "AR"
        }
      ],
      "duration": "02:03:32",
      "round": "Round of 16",
      "date": "2016-02-13"
    },
    {
      "players": [
        {
          "is_winner": false,
          "set_games": [
            "3",
            "2"
          ],
          "name": "Guilherme Clezar",
          "country": "BR"
        },
        {
          "is_winner": true,
          "set_games": [
            "6",
            "6"
          ],
          "name": "Daniel Gimeno",
          "country": "ES"
        }
      ],
      "duration": "01:23:55",
      "round": "Round of 16",
      "date": "2016-02-13"
    },
    {
      "players": [
        {
          "is_winner": false,
          "set_games": [
            "7",
            "4",
            "0"
          ],
          "name": "Jose Pereira",
          "country": "BR"
        },
        {
          "is_winner": true,
          "set_games": [
            "6",
            "6",
            "6"
          ],
          "name": "Albert Montanes",
          "country": "ES"
        }
      ],
      "duration": "02:10:47",
      "round": "Round of 16",
      "date": "2016-02-13"
    },
    {
      "players": [
        {
          "is_winner": true,
          "set_games": [
            "6",
            "6"
          ],
          "name": "Paul-Henri Mathieu",
          "country": "FR"
        },
        {
          "is_winner": false,
          "set_games": [
            "3",
            "4"
          ],
          "name": "Andre Ghem",
          "country": "BR"
        }
      ],
      "duration": "01:23:01",
      "round": "Round of 16",
      "date": "2016-02-13"
    },
    {
      "players": [
        {
          "is_winner": true,
          "set_games": [
            "6",
            "6"
          ],
          "name": "Rogerio Dutra Silva",
          "country": "BR"
        },
        {
          "is_winner": false,
          "set_games": [
            "2",
            "2"
          ],
          "name": "Hans Podlipnik",
          "country": "CL"
        }
      ],
      "duration": "01:17:26",
      "round": "Round of 16",
      "date": "2016-02-13"
    },
    {
      "players": [
        {
          "is_winner": true,
          "set_games": [
            "6",
            "6"
          ],
          "name": "Taro Daniel",
          "country": "JP"
        },
        {
          "is_winner": false,
          "set_games": [
            "4",
            "4"
          ],
          "name": "Orlando Luz",
          "country": "BR"
        }
      ],
      "duration": "01:30:48",
      "round": "Round of 16",
      "date": "2016-02-13"
    },
    {
      "players": [
        {
          "is_winner": true,
          "set_games": [
            "6",
            "5"
          ],
          "name": "Facundo Bagnis",
          "country": "AR"
        },
        {
          "is_winner": false,
          "set_games": [
            "4",
            "2"
          ],
          "name": "Albert Montanes",
          "country": "ES"
        }
      ],
      "duration": "N/A",
      "round": "Quarter-Final",
      "date": "2016-02-14"
    },
    {
      "players": [
        {
          "is_winner": false,
          "set_games": [
            "4",
            "2"
          ],
          "name": "Paul-Henri Mathieu",
          "country": "FR"
        },
        {
          "is_winner": true,
          "set_games": [
            "6",
            "2"
          ],
          "name": "Daniel Gimeno",
          "country": "ES"
        }
      ],
      "duration": "N/A",
      "round": "Quarter-Final",
      "date": "2016-02-14"
    },
    {
      "players": [
        {
          "is_winner": false,
          "set_games": [
            "6",
            "5",
            "2"
          ],
          "name": "Rogerio Dutra Silva",
          "country": "BR"
        },
        {
          "is_winner": true,
          "set_games": [
            "1",
            "7",
            "6"
          ],
          "name": "Gastao Elias",
          "country": "PT"
        }
      ],
      "duration": "02:14:02",
      "round": "Quarter-Final",
      "date": "2016-02-14"
    },
    {
      "players": [
        {
          "is_winner": true,
          "set_games": [
            "3",
            "6",
            "6"
          ],
          "name": "Taro Daniel",
          "country": "JP"
        },
        {
          "is_winner": false,
          "set_games": [
            "6",
            "2",
            "3"
          ],
          "name": "Facundo Arguello",
          "country": "AR"
        }
      ],
      "duration": "02:09:04",
      "round": "Quarter-Final",
      "date": "2016-02-14"
    }
  ]
}