{
  "name": "2016 Australian Open, Qualification WTA Grand Slam (Women's Singles)",
  "country": "Australia",
  "gender": "female",
  "location": "Melbourne",
  "surface": "Hard",
  "events": [
    {
      "players": [
        {
          "is_winner": false,
          "set_games": [
            "3",
            "3"
          ],
          "name": "Aleksandra Wozniak",
          "country": "CA"
        },
        {
          "is_winner": true,
          "set_games": [
            "6",
            "6"
          ],
          "name": "Kristina Kucova",
          "country": "SK"
        }
      ],
      "duration": "01:08:51",
      "round": "Round of 128",
      "date": "2016-01-13"
    },
    {
      "players": [
        {
          "is_winner": true,
          "set_games": [
            "6",
            "6"
          ],
          "name": "Anastasija Sevastova",
          "country": "LV"
        },
        {
          "is_winner": false,
          "set_games": [
            "3",
            "2"
          ],
          "name": "Destanee Aiava",
          "country": "AU"
        }
      ],
      "duration": "00:41:43",
      "round": "Round of 128",
      "date": "2016-01-13"
    },
    {
      "players": [
        {
          "is_winner": true,
          "set_games": [
            "7",
            "6"
          ],
          "name": "Elise Mertens",
          "country": "BE"
        },
        {
          "is_winner": false,
          "set_games": [
            "5",
            "2"
          ],
          "name": "Heidi El Tabakh",
          "country": "CA"
        }
      ],
      "duration": "01:16:20",
      "round": "Round of 128",
      "date": "2016-01-13"
    },
    {
      "players": [
        {
          "is_winner": true,
          "set_games": [
            "7",
            "4",
            "6"
          ],
          "name": "Francesca Schiavone",
          "country": "IT"
        },
        {
          "is_winner": false,
          "set_games": [
            "6",
            "6",
            "0"
          ],
          "name": "An-Sophie Mestach",
          "country": "BE"
        }
      ],
      "duration": "02:30:36",
      "round": "Round of 128",
      "date": "2016-01-13"
    },
    {
      "players": [
        {
          "is_winner": false,
          "set_games": [
            "0",
            "3"
          ],
          "name": "Irina Khromacheva",
          "country": "RU"
        },
        {
          "is_winner": true,
          "set_games": [
            "6",
            "6"
          ],
          "name": "Tereza Martincova",
          "country": "CZ"
        }
      ],
      "duration": "00:42:26",
      "round": "Round of 128",
      "date": "2016-01-13"
    },
    {
      "players": [
        {
          "is_winner": true,
          "set_games": [
            "6",
            "7"
          ],
          "name": "Julia Boserup",
          "country": "US"
        },
        {
          "is_winner": false,
          "set_games": [
            "2",
            "5"
          ],
          "name": "Mayo Hibi",
          "country": "JP"
        }
      ],
      "duration": "01:32:21",
      "round": "Round of 128",
      "date": "2016-01-13"
    },
    {
      "players": [
        {
          "is_winner": false,
          "set_games": [
            "2",
            "4"
          ],
          "name": "Kateryna Kozlova",
          "country": "UA"
        },
        {
          "is_winner": true,
          "set_games": [
            "6",
            "6"
          ],
          "name": "Tamira Paszek",
          "country": "AT"
        }
      ],
      "duration": "01:32:02",
      "round": "Round of 128",
      "date": "2016-01-13"
    },
    {
      "players": [
        {
          "is_winner": false,
          "set_games": [
            "2",
            "0"
          ],
          "name": "Laura Pous",
          "country": "ES"
        },
        {
          "is_winner": true,
          "set_games": [
            "6",
            "3"
          ],
          "name": "Kai-Chen Chang",
          "country": "TW"
        }
      ],
      "duration": "00:42:48",
      "round": "Round of 128",
      "date": "2016-01-13"
    },
    {
      "players": [
        {
          "is_winner": false,
          "set_games": [
            "3",
            "2"
          ],
          "name": "Mandy Minella",
          "country": "LU"
        },
        {
          "is_winner": true,
          "set_games": [
            "6",
            "6"
          ],
          "name": "Shuai Zhang",
          "country": "CN"
        }
      ],
      "duration": "01:03:34",
      "round": "Round of 128",
      "date": "2016-01-13"
    },
    {
      "players": [
        {
          "is_winner": false,
          "set_games": [
            "2",
            "1"
          ],
          "name": "Maria Irigoyen",
          "country": "AR"
        },
        {
          "is_winner": true,
          "set_games": [
            "6",
            "6"
          ],
          "name": "Richel Hogenkamp",
          "country": "NL"
        }
      ],
      "duration": "01:01:25",
      "round": "Round of 128",
      "date": "2016-01-13"
    },
    {
      "players": [
        {
          "is_winner": false,
          "set_games": [
            "6",
            "2",
            "5"
          ],
          "name": "Mathilde Johansson",
          "country": "FR"
        },
        {
          "is_winner": true,
          "set_games": [
            "1",
            "6",
            "7"
          ],
          "name": "Zhaoxuan Yang",
          "country": "CN"
        }
      ],
      "duration": "01:52:27",
      "round": "Round of 128",
      "date": "2016-01-13"
    },
    {
      "players": [
        {
          "is_winner": false,
          "set_games": [
            "3",
            "6",
            "3"
          ],
          "name": "Naomi Broady",
          "country": "GB"
        },
        {
          "is_winner": true,
          "set_games": [
            "6",
            "2",
            "6"
          ],
          "name": "Alize Lim",
          "country": "FR"
        }
      ],
      "duration": "01:50:08",
      "round": "Round of 128",
      "date": "2016-01-13"
    },
    {
      "players": [
        {
          "is_winner": true,
          "set_games": [
            "6",
            "6"
          ],
          "name": "Nicole Gibbs",
          "country": "US"
        },
        {
          "is_winner": false,
          "set_games": [
            "2",
            "2"
          ],
          "name": "Olivia Tjandramulia",
          "country": "AU"
        }
      ],
      "duration": "01:26:01",
      "round": "Round of 128",
      "date": "2016-01-13"
    },
    {
      "players": [
        {
          "is_winner": false,
          "set_games": [
            "6",
            "3"
          ],
          "name": "Olga Savchuk",
          "country": "UA"
        },
        {
          "is_winner": true,
          "set_games": [
            "7",
            "6"
          ],
          "name": "Tereza Smitkova",
          "country": "CZ"
        }
      ],
      "duration": "01:29:58",
      "round": "Round of 128",
      "date": "2016-01-13"
    },
    {
      "players": [
        {
          "is_winner": false,
          "set_games": [
            "1",
            "1"
          ],
          "name": "Olivia Rogowska",
          "country": "AU"
        },
        {
          "is_winner": true,
          "set_games": [
            "6",
            "6"
          ],
          "name": "Ivana Jorovic",
          "country": "RS"
        }
      ],
      "duration": "00:49:08",
      "round": "Round of 128",
      "date": "2016-01-13"
    },
    {
      "players": [
        {
          "is_winner": false,
          "set_games": [
            "6",
            "7",
            "3"
          ],
          "name": "Patricia Maria Tig",
          "country": "RO"
        },
        {
          "is_winner": true,
          "set_games": [
            "7",
            "6",
            "6"
          ],
          "name": "Barbora Krejcikova",
          "country": "CZ"
        }
      ],
      "duration": "02:55:42",
      "round": "Round of 128",
      "date": "2016-01-13"
    },
    {
      "players": [
        {
          "is_winner": true,
          "set_games": [
            "2",
            "6",
            "6"
          ],
          "name": "Paula Kania",
          "country": "PL"
        },
        {
          "is_winner": false,
          "set_games": [
            "6",
            "4",
            "2"
          ],
          "name": "Maria Teresa Torro",
          "country": "ES"
        }
      ],
      "duration": "01:32:02",
      "round": "Round of 128",
      "date": "2016-01-13"
    },
    {
      "players": [
        {
          "is_winner": true,
          "set_games": [
            "7",
            "6"
          ],
          "name": "Qiang Wang",
          "country": "CN"
        },
        {
          "is_winner": false,
          "set_games": [
            "5",
            "2"
          ],
          "name": "Misa Eguchi",
          "country": "JP"
        }
      ],
      "duration": "01:32:19",
      "round": "Round of 128",
      "date": "2016-01-13"
    },
    {
      "players": [
        {
          "is_winner": false,
          "set_games": [
            "3",
            "2"
          ],
          "name": "Sara Tomic",
          "country": "AU"
        },
        {
          "is_winner": true,
          "set_games": [
            "6",
            "6"
          ],
          "name": "Jana Fett",
          "country": "HR"
        }
      ],
      "duration": "01:02:26",
      "round": "Round of 128",
      "date": "2016-01-13"
    },
    {
      "players": [
        {
          "is_winner": true,
          "set_games": [
            "6",
            "6"
          ],
          "name": "Stephanie Foretz Gacon",
          "country": "FR"
        },
        {
          "is_winner": false,
          "set_games": [
            "1",
            "1"
          ],
          "name": "Jovana Jaksic",
          "country": "RS"
        }
      ],
      "duration": "00:56:12",
      "round": "Round of 128",
      "date": "2016-01-13"
    },
    {
      "players": [
        {
          "is_winner": false,
          "set_games": [
            "4",
            "1"
          ],
          "name": "Stephanie Vogt",
          "country": "LI"
        },
        {
          "is_winner": true,
          "set_games": [
            "6",
            "6"
          ],
          "name": "Arina Rodionova",
          "country": "AU"
        }
      ],
      "duration": "01:16:45",
      "round": "Round of 128",
      "date": "2016-01-13"
    },
    {
      "players": [
        {
          "is_winner": true,
          "set_games": [
            "2",
            "6",
            "8"
          ],
          "name": "Vera Dushevina",
          "country": "RU"
        },
        {
          "is_winner": false,
          "set_games": [
            "6",
            "2",
            "6"
          ],
          "name": "Ipek Soylu",
          "country": "TR"
        }
      ],
      "duration": "01:49:35",
      "round": "Round of 128",
      "date": "2016-01-13"
    },
    {
      "players": [
        {
          "is_winner": true,
          "set_games": [
            "6",
            "6"
          ],
          "name": "Virginie Razzano",
          "country": "FR"
        },
        {
          "is_winner": false,
          "set_games": [
            "4",
            "3"
          ],
          "name": "Kristie Ahn",
          "country": "US"
        }
      ],
      "duration": "01:44:59",
      "round": "Round of 128",
      "date": "2016-01-13"
    },
    {
      "players": [
        {
          "is_winner": true,
          "set_games": [
            "6",
            "7"
          ],
          "name": "Yafan Wang",
          "country": "CN"
        },
        {
          "is_winner": false,
          "set_games": [
            "3",
            "5"
          ],
          "name": "Katerina Stewart",
          "country": "US"
        }
      ],
      "duration": "01:14:28",
      "round": "Round of 128",
      "date": "2016-01-13"
    },
    {
      "players": [
        {
          "is_winner": true,
          "set_games": [
            "6",
            "6"
          ],
          "name": "Yingying Duan",
          "country": "CN"
        },
        {
          "is_winner": false,
          "set_games": [
            "1",
            "2"
          ],
          "name": "Petra Martic",
          "country": "HR"
        }
      ],
      "duration": "00:49:18",
      "round": "Round of 128",
      "date": "2016-01-13"
    },
    {
      "players": [
        {
          "is_winner": false,
          "set_games": [
            "3",
            "1"
          ],
          "name": "Alexa Glatch",
          "country": "US"
        },
        {
          "is_winner": true,
          "set_games": [
            "6",
            "6"
          ],
          "name": "Luksika Kumkhum",
          "country": "TH"
        }
      ],
      "duration": "01:05:56",
      "round": "Round of 128",
      "date": "2016-01-14"
    },
    {
      "players": [
        {
          "is_winner": false,
          "set_games": [
            "6",
            "4",
            "1"
          ],
          "name": "Alize Lim",
          "country": "FR"
        },
        {
          "is_winner": true,
          "set_games": [
            "1",
            "6",
            "6"
          ],
          "name": "Yafan Wang",
          "country": "CN"
        }
      ],
      "duration": "02:22:55",
      "round": "Round of 64",
      "date": "2016-01-14"
    },
    {
      "players": [
        {
          "is_winner": false,
          "set_games": [
            "1",
            "6",
            "3"
          ],
          "name": "Amandine Hesse",
          "country": "FR"
        },
        {
          "is_winner": true,
          "set_games": [
            "6",
            "3",
            "6"
          ],
          "name": "Julia Glushko",
          "country": "IL"
        }
      ],
      "duration": "01:45:13",
      "round": "Round of 64",
      "date": "2016-01-14"
    },
    {
      "players": [
        {
          "is_winner": true,
          "set_games": [
            "6",
            "6"
          ],
          "name": "Anastasija Sevastova",
          "country": "LV"
        },
        {
          "is_winner": false,
          "set_games": [
            "3",
            "1"
          ],
          "name": "Vera Dushevina",
          "country": "RU"
        }
      ],
      "duration": "00:49:27",
      "round": "Round of 64",
      "date": "2016-01-14"
    },
    {
      "players": [
        {
          "is_winner": true,
          "set_games": [
            "6",
            "6"
          ],
          "name": "Barbora Krejcikova",
          "country": "CZ"
        },
        {
          "is_winner": false,
          "set_games": [
            "3",
            "2"
          ],
          "name": "Hiroko Kuwata",
          "country": "JP"
        }
      ],
      "duration": "01:03:43",
      "round": "Round of 64",
      "date": "2016-01-14"
    },
    {
      "players": [
        {
          "is_winner": false,
          "set_games": [
            "3",
            "1"
          ],
          "name": "Cindy Burger",
          "country": "NL"
        },
        {
          "is_winner": true,
          "set_games": [
            "6",
            "6"
          ],
          "name": "Sara Sorribes",
          "country": "ES"
        }
      ],
      "duration": "00:04:25",
      "round": "Round of 128",
      "date": "2016-01-14"
    },
    {
      "players": [
        {
          "is_winner": false,
          "set_games": [
            "3",
            "6",
            "7"
          ],
          "name": "Elena Vesnina",
          "country": "RU"
        },
        {
          "is_winner": true,
          "set_games": [
            "6",
            "4",
            "9"
          ],
          "name": "Lin Zhu",
          "country": "CN"
        }
      ],
      "duration": "02:45:25",
      "round": "Round of 128",
      "date": "2016-01-14"
    },
    {
      "players": [
        {
          "is_winner": false,
          "set_games": [
            "6",
            "4",
            "2"
          ],
          "name": "Elise Mertens",
          "country": "BE"
        },
        {
          "is_winner": true,
          "set_games": [
            "2",
            "6",
            "6"
          ],
          "name": "Maria Sakkari",
          "country": "GR"
        }
      ],
      "duration": "02:18:09",
      "round": "Round of 64",
      "date": "2016-01-14"
    },
    {
      "players": [
        {
          "is_winner": false,
          "set_games": [
            "1",
            "3"
          ],
          "name": "Eri Hozumi",
          "country": "JP"
        },
        {
          "is_winner": true,
          "set_games": [
            "6",
            "6"
          ],
          "name": "Julia Glushko",
          "country": "IL"
        }
      ],
      "duration": "00:51:06",
      "round": "Round of 128",
      "date": "2016-01-14"
    },
    {
      "players": [
        {
          "is_winner": false,
          "set_games": [
            "1",
            "6",
            "1"
          ],
          "name": "Francesca Schiavone",
          "country": "IT"
        },
        {
          "is_winner": true,
          "set_games": [
            "6",
            "4",
            "6"
          ],
          "name": "Virginie Razzano",
          "country": "FR"
        }
      ],
      "duration": "01:55:55",
      "round": "Round of 64",
      "date": "2016-01-14"
    },
    {
      "players": [
        {
          "is_winner": true,
          "set_games": [
            "6",
            "6",
            "12"
          ],
          "name": "Hiroko Kuwata",
          "country": "JP"
        },
        {
          "is_winner": false,
          "set_games": [
            "3",
            "7",
            "10"
          ],
          "name": "Silvia Soler",
          "country": "ES"
        }
      ],
      "duration": "00:56:58",
      "round": "Round of 128",
      "date": "2016-01-14"
    },
    {
      "players": [
        {
          "is_winner": true,
          "set_games": [
            "6",
            "6"
          ],
          "name": "Ivana Jorovic",
          "country": "RS"
        },
        {
          "is_winner": false,
          "set_games": [
            "4",
            "2"
          ],
          "name": "Kai-Chen Chang",
          "country": "TW"
        }
      ],
      "duration": "01:29:15",
      "round": "Round of 64",
      "date": "2016-01-14"
    },
    {
      "players": [
        {
          "is_winner": false,
          "set_games": [
            "4",
            "5"
          ],
          "name": "Jana Cepelova",
          "country": "SK"
        },
        {
          "is_winner": true,
          "set_games": [
            "6",
            "7"
          ],
          "name": "Sachia Vickery",
          "country": "US"
        }
      ],
      "duration": "01:51:50",
      "round": "Round of 64",
      "date": "2016-01-14"
    },
    {
      "players": [
        {
          "is_winner": false,
          "set_games": [
            "2",
            "3"
          ],
          "name": "Jessica Pegula",
          "country": "US"
        },
        {
          "is_winner": true,
          "set_games": [
            "6",
            "6"
          ],
          "name": "Kailin Zhang",
          "country": "CN"
        }
      ],
      "duration": "01:22:53",
      "round": "Round of 64",
      "date": "2016-01-14"
    },
    {
      "players": [
        {
          "is_winner": true,
          "set_games": [
            "6",
            "7"
          ],
          "name": "Julia Boserup",
          "country": "US"
        },
        {
          "is_winner": false,
          "set_games": [
            "2",
            "5"
          ],
          "name": "Paula Kania",
          "country": "PL"
        }
      ],
      "duration": "01:33:10",
      "round": "Round of 64",
      "date": "2016-01-14"
    },
    {
      "players": [
        {
          "is_winner": false,
          "set_games": [
            "2",
            "7",
            "4"
          ],
          "name": "Kimiko Date Krumm",
          "country": "JP"
        },
        {
          "is_winner": true,
          "set_games": [
            "6",
            "6",
            "6"
          ],
          "name": "Amandine Hesse",
          "country": "FR"
        }
      ],
      "duration": "01:50:52",
      "round": "Round of 128",
      "date": "2016-01-14"
    },
    {
      "players": [
        {
          "is_winner": true,
          "set_games": [
            "7",
            "6"
          ],
          "name": "Kristina Kucova",
          "country": "SK"
        },
        {
          "is_winner": false,
          "set_games": [
            "5",
            "0"
          ],
          "name": "Tereza Smitkova",
          "country": "CZ"
        }
      ],
      "duration": "01:16:21",
      "round": "Round of 64",
      "date": "2016-01-14"
    },
    {
      "players": [
        {
          "is_winner": true,
          "set_games": [
            "7",
            "6"
          ],
          "name": "Kristyna Pliskova",
          "country": "CZ"
        },
        {
          "is_winner": false,
          "set_games": [
            "5",
            "1"
          ],
          "name": "Ysaline Bonaventure",
          "country": "BE"
        }
      ],
      "duration": "01:03:56",
      "round": "Round of 64",
      "date": "2016-01-14"
    },
    {
      "players": [
        {
          "is_winner": true,
          "set_games": [
            "6",
            "4",
            "6"
          ],
          "name": "Kristyna Pliskova",
          "country": "CZ"
        },
        {
          "is_winner": false,
          "set_games": [
            "4",
            "6",
            "3"
          ],
          "name": "Shahar Peer",
          "country": "IL"
        }
      ],
      "duration": "01:45:04",
      "round": "Round of 128",
      "date": "2016-01-14"
    },
    {
      "players": [
        {
          "is_winner": true,
          "set_games": [
            "7",
            "6"
          ],
          "name": "Lesley Kerkhove",
          "country": "NL"
        },
        {
          "is_winner": false,
          "set_games": [
            "6",
            "3"
          ],
          "name": "Rebecca Peterson",
          "country": "SE"
        }
      ],
      "duration": "01:42:21",
      "round": "Round of 128",
      "date": "2016-01-14"
    },
    {
      "players": [
        {
          "is_winner": true,
          "set_games": [
            "6",
            "6"
          ],
          "name": "Lin Zhu",
          "country": "CN"
        },
        {
          "is_winner": false,
          "set_games": [
            "3",
            "2"
          ],
          "name": "Sara Sorribes",
          "country": "ES"
        }
      ],
      "duration": "01:16:04",
      "round": "Round of 64",
      "date": "2016-01-14"
    },
    {
      "players": [
        {
          "is_winner": false,
          "set_games": [
            "1",
            "1"
          ],
          "name": "Marcela Zacarias",
          "country": "MX"
        },
        {
          "is_winner": true,
          "set_games": [
            "6",
            "6"
          ],
          "name": "Alexandra Panova",
          "country": "RU"
        }
      ],
      "duration": "00:55:18",
      "round": "Round of 128",
      "date": "2016-01-14"
    },
    {
      "players": [
        {
          "is_winner": false,
          "set_games": [
            "1",
            "1"
          ],
          "name": "Maria Jose Martinez",
          "country": "ES"
        },
        {
          "is_winner": true,
          "set_games": [
            "6",
            "6"
          ],
          "name": "Tamira Paszek",
          "country": "AT"
        }
      ],
      "duration": "01:15:23",
      "round": "Round of 64",
      "date": "2016-01-14"
    },
    {
      "players": [
        {
          "is_winner": true,
          "set_games": [
            "1",
            "7",
            "6"
          ],
          "name": "Maria Jose Martinez",
          "country": "ES"
        },
        {
          "is_winner": false,
          "set_games": [
            "6",
            "6",
            "1"
          ],
          "name": "Andrea Hlavackova",
          "country": "CZ"
        }
      ],
      "duration": "00:13:31",
      "round": "Round of 128",
      "date": "2016-01-14"
    },
    {
      "players": [
        {
          "is_winner": true,
          "set_games": [
            "4",
            "6",
            "7"
          ],
          "name": "Maria Sakkari",
          "country": "GR"
        },
        {
          "is_winner": false,
          "set_games": [
            "6",
            "4",
            "5"
          ],
          "name": "Cagla Buyukakcay",
          "country": "TR"
        }
      ],
      "duration": "01:47:00",
      "round": "Round of 128",
      "date": "2016-01-14"
    },
    {
      "players": [
        {
          "is_winner": false,
          "set_games": [
            "2",
            "3"
          ],
          "name": "Maria Sanchez",
          "country": "US"
        },
        {
          "is_winner": true,
          "set_games": [
            "6",
            "6"
          ],
          "name": "Michelle Larcher De Brito",
          "country": "PT"
        }
      ],
      "duration": "01:06:13",
      "round": "Round of 64",
      "date": "2016-01-14"
    },
    {
      "players": [
        {
          "is_winner": true,
          "set_games": [
            "6",
            "6"
          ],
          "name": "Maria Sanchez",
          "country": "US"
        },
        {
          "is_winner": false,
          "set_games": [
            "4",
            "2"
          ],
          "name": "Fangzhou Liu",
          "country": "CN"
        }
      ],
      "duration": "01:06:48",
      "round": "Round of 128",
      "date": "2016-01-14"
    },
    {
      "players": [
        {
          "is_winner": true,
          "set_games": [
            "0",
            "6",
            "7"
          ],
          "name": "Michelle Larcher De Brito",
          "country": "PT"
        },
        {
          "is_winner": false,
          "set_games": [
            "6",
            "4",
            "5"
          ],
          "name": "Marina Erakovic",
          "country": "NZ"
        }
      ],
      "duration": "00:36:24",
      "round": "Round of 128",
      "date": "2016-01-14"
    },
    {
      "players": [
        {
          "is_winner": false,
          "set_games": [
            "0",
            "3"
          ],
          "name": "Miyu Kato",
          "country": "JP"
        },
        {
          "is_winner": true,
          "set_games": [
            "6",
            "6"
          ],
          "name": "Naomi Osaka",
          "country": "JP"
        }
      ],
      "duration": "00:53:42",
      "round": "Round of 128",
      "date": "2016-01-14"
    },
    {
      "players": [
        {
          "is_winner": false,
          "set_games": [
            "1",
            "2"
          ],
          "name": "Naiktha Bains",
          "country": "AU"
        },
        {
          "is_winner": true,
          "set_games": [
            "6",
            "6"
          ],
          "name": "Sachia Vickery",
          "country": "US"
        }
      ],
      "duration": "01:19:50",
      "round": "Round of 128",
      "date": "2016-01-14"
    },
    {
      "players": [
        {
          "is_winner": true,
          "set_games": [
            "6",
            "7"
          ],
          "name": "Naomi Osaka",
          "country": "JP"
        },
        {
          "is_winner": false,
          "set_games": [
            "2",
            "6"
          ],
          "name": "Alexandra Panova",
          "country": "RU"
        }
      ],
      "duration": "01:32:02",
      "round": "Round of 64",
      "date": "2016-01-14"
    },
    {
      "players": [
        {
          "is_winner": true,
          "set_games": [
            "6",
            "7"
          ],
          "name": "Nicole Gibbs",
          "country": "US"
        },
        {
          "is_winner": false,
          "set_games": [
            "2",
            "6"
          ],
          "name": "Jana Fett",
          "country": "HR"
        }
      ],
      "duration": "01:35:56",
      "round": "Round of 64",
      "date": "2016-01-14"
    },
    {
      "players": [
        {
          "is_winner": false,
          "set_games": [
            "3",
            "2"
          ],
          "name": "Pauline Parmentier",
          "country": "FR"
        },
        {
          "is_winner": true,
          "set_games": [
            "6",
            "6"
          ],
          "name": "Risa Ozaki",
          "country": "JP"
        }
      ],
      "duration": "01:17:02",
      "round": "Round of 128",
      "date": "2016-01-14"
    },
    {
      "players": [
        {
          "is_winner": true,
          "set_games": [
            "6",
            "5",
            "6"
          ],
          "name": "Qiang Wang",
          "country": "CN"
        },
        {
          "is_winner": false,
          "set_games": [
            "4",
            "7",
            "2"
          ],
          "name": "Zhaoxuan Yang",
          "country": "CN"
        }
      ],
      "duration": "01:59:42",
      "round": "Round of 64",
      "date": "2016-01-14"
    },
    {
      "players": [
        {
          "is_winner": false,
          "set_games": [
            "2",
            "1"
          ],
          "name": "Risa Ozaki",
          "country": "JP"
        },
        {
          "is_winner": true,
          "set_games": [
            "6",
            "6"
          ],
          "name": "Maryna Zanevska",
          "country": "UA"
        }
      ],
      "duration": "01:14:25",
      "round": "Round of 64",
      "date": "2016-01-14"
    },
    {
      "players": [
        {
          "is_winner": false,
          "set_games": [
            "2",
            "0"
          ],
          "name": "Sesil Karatantcheva",
          "country": "BG"
        },
        {
          "is_winner": true,
          "set_games": [
            "6",
            "6"
          ],
          "name": "Jessica Pegula",
          "country": "US"
        }
      ],
      "duration": "00:58:49",
      "round": "Round of 128",
      "date": "2016-01-14"
    },
    {
      "players": [
        {
          "is_winner": true,
          "set_games": [
            "7",
            "6"
          ],
          "name": "Stefanie Voegele",
          "country": "CH"
        },
        {
          "is_winner": false,
          "set_games": [
            "6",
            "3"
          ],
          "name": "Tereza Mihalikova",
          "country": "SK"
        }
      ],
      "duration": "01:45:04",
      "round": "Round of 128",
      "date": "2016-01-14"
    },
    {
      "players": [
        {
          "is_winner": false,
          "set_games": [
            "1",
            "3"
          ],
          "name": "Stephanie Foretz Gacon",
          "country": "FR"
        },
        {
          "is_winner": true,
          "set_games": [
            "6",
            "6"
          ],
          "name": "Richel Hogenkamp",
          "country": "NL"
        }
      ],
      "duration": "00:58:43",
      "round": "Round of 64",
      "date": "2016-01-14"
    },
    {
      "players": [
        {
          "is_winner": false,
          "set_games": [
            "2",
            "3"
          ],
          "name": "Su-Jeong Jang",
          "country": "KR"
        },
        {
          "is_winner": true,
          "set_games": [
            "6",
            "6"
          ],
          "name": "Kailin Zhang",
          "country": "CN"
        }
      ],
      "duration": "01:17:14",
      "round": "Round of 128",
      "date": "2016-01-14"
    },
    {
      "players": [
        {
          "is_winner": false,
          "set_games": [
            "1",
            "6"
          ],
          "name": "Tereza Martincova",
          "country": "CZ"
        },
        {
          "is_winner": true,
          "set_games": [
            "6",
            "7"
          ],
          "name": "Shuai Zhang",
          "country": "CN"
        }
      ],
      "duration": "01:12:48",
      "round": "Round of 64",
      "date": "2016-01-14"
    },
    {
      "players": [
        {
          "is_winner": false,
          "set_games": [
            "2",
            "4"
          ],
          "name": "Veronica Cepede",
          "country": "PY"
        },
        {
          "is_winner": true,
          "set_games": [
            "6",
            "6"
          ],
          "name": "Jana Cepelova",
          "country": "SK"
        }
      ],
      "duration": "01:07:57",
      "round": "Round of 128",
      "date": "2016-01-14"
    },
    {
      "players": [
        {
          "is_winner": true,
          "set_games": [
            "7",
            "6"
          ],
          "name": "Viktorija Golubic",
          "country": "CH"
        },
        {
          "is_winner": false,
          "set_games": [
            "5",
            "2"
          ],
          "name": "Lesley Kerkhove",
          "country": "NL"
        }
      ],
      "duration": "01:14:46",
      "round": "Round of 64",
      "date": "2016-01-14"
    },
    {
      "players": [
        {
          "is_winner": true,
          "set_games": [
            "4",
            "6",
            "6"
          ],
          "name": "Viktorija Golubic",
          "country": "CH"
        },
        {
          "is_winner": false,
          "set_games": [
            "6",
            "4",
            "1"
          ],
          "name": "Alla Kudryavtseva",
          "country": "RU"
        }
      ],
      "duration": "02:19:36",
      "round": "Round of 128",
      "date": "2016-01-14"
    },
    {
      "players": [
        {
          "is_winner": false,
          "set_games": [
            "1"
          ],
          "name": "Yingying Duan",
          "country": "CN"
        },
        {
          "is_winner": true,
          "set_games": [
            "2"
          ],
          "name": "Arina Rodionova",
          "country": "AU"
        }
      ],
      "duration": "00:22:03",
      "round": "Round of 64",
      "date": "2016-01-14"
    },
    {
      "players": [
        {
          "is_winner": true,
          "set_games": [
            "6",
            "6"
          ],
          "name": "Ysaline Bonaventure",
          "country": "BE"
        },
        {
          "is_winner": false,
          "set_games": [
            "2",
            "4"
          ],
          "name": "Zoe Hives",
          "country": "AU"
        }
      ],
      "duration": "01:08:26",
      "round": "Round of 128",
      "date": "2016-01-14"
    },
    {
      "players": [
        {
          "is_winner": false,
          "set_games": [
            "5",
            "7",
            "4"
          ],
          "name": "Yuxuan Zhang",
          "country": "CN"
        },
        {
          "is_winner": true,
          "set_games": [
            "7",
            "6",
            "6"
          ],
          "name": "Maryna Zanevska",
          "country": "UA"
        }
      ],
      "duration": "02:15:47",
      "round": "Round of 128",
      "date": "2016-01-14"
    },
    {
      "players": [
        {
          "is_winner": true,
          "set_games": [
            "4",
            "6",
            "6"
          ],
          "name": "Anastasija Sevastova",
          "country": "LV"
        },
        {
          "is_winner": false,
          "set_games": [
            "6",
            "3",
            "2"
          ],
          "name": "Julia Boserup",
          "country": "US"
        }
      ],
      "duration": "01:37:28",
      "round": "Round of 32",
      "date": "2016-01-15"
    },
    {
      "players": [
        {
          "is_winner": false,
          "set_games": [
            "2",
            "1"
          ],
          "name": "Arina Rodionova",
          "country": "AU"
        },
        {
          "is_winner": true,
          "set_games": [
            "6",
            "6"
          ],
          "name": "Viktorija Golubic",
          "country": "CH"
        }
      ],
      "duration": "01:04:05",
      "round": "Round of 32",
      "date": "2016-01-15"
    },
    {
      "players": [
        {
          "is_winner": false,
          "set_games": [
            "4",
            "2"
          ],
          "name": "Barbora Krejcikova",
          "country": "CZ"
        },
        {
          "is_winner": true,
          "set_games": [
            "6",
            "6"
          ],
          "name": "Tamira Paszek",
          "country": "AT"
        }
      ],
      "duration": "01:26:48",
      "round": "Round of 32",
      "date": "2016-01-15"
    },
    {
      "players": [
        {
          "is_winner": false,
          "set_games": [
            "3",
            "2"
          ],
          "name": "Lin Zhu",
          "country": "CN"
        },
        {
          "is_winner": true,
          "set_games": [
            "6",
            "6"
          ],
          "name": "Maria Sakkari",
          "country": "GR"
        }
      ],
      "duration": "01:14:33",
      "round": "Round of 32",
      "date": "2016-01-15"
    },
    {
      "players": [
        {
          "is_winner": true,
          "set_games": [
            "6",
            "7"
          ],
          "name": "Maryna Zanevska",
          "country": "UA"
        },
        {
          "is_winner": false,
          "set_games": [
            "3",
            "5"
          ],
          "name": "Michelle Larcher De Brito",
          "country": "PT"
        }
      ],
      "duration": "01:24:20",
      "round": "Round of 32",
      "date": "2016-01-15"
    },
    {
      "players": [
        {
          "is_winner": true,
          "set_games": [
            "6",
            "6"
          ],
          "name": "Nicole Gibbs",
          "country": "US"
        },
        {
          "is_winner": false,
          "set_games": [
            "3",
            "3"
          ],
          "name": "Ivana Jorovic",
          "country": "RS"
        }
      ],
      "duration": "01:09:08",
      "round": "Round of 32",
      "date": "2016-01-15"
    },
    {
      "players": [
        {
          "is_winner": true,
          "set_games": [
            "6",
            "6"
          ],
          "name": "Qiang Wang",
          "country": "CN"
        },
        {
          "is_winner": false,
          "set_games": [
            "2",
            "3"
          ],
          "name": "Richel Hogenkamp",
          "country": "NL"
        }
      ],
      "duration": "00:57:55",
      "round": "Round of 32",
      "date": "2016-01-15"
    },
    {
      "players": [
        {
          "is_winner": false,
          "set_games": [
            "3",
            "4"
          ],
          "name": "Stefanie Voegele",
          "country": "CH"
        },
        {
          "is_winner": true,
          "set_games": [
            "6",
            "6"
          ],
          "name": "Luksika Kumkhum",
          "country": "TH"
        }
      ],
      "duration": "01:26:47",
      "round": "Round of 64",
      "date": "2016-01-15"
    },
    {
      "players": [
        {
          "is_winner": false,
          "set_games": [
            "6",
            "2",
            "6"
          ],
          "name": "Virginie Razzano",
          "country": "FR"
        },
        {
          "is_winner": true,
          "set_games": [
            "4",
            "6",
            "8"
          ],
          "name": "Shuai Zhang",
          "country": "CN"
        }
      ],
      "duration": "02:26:26",
      "round": "Round of 32",
      "date": "2016-01-15"
    },
    {
      "players": [
        {
          "is_winner": true,
          "set_games": [
            "5",
            "7",
            "6"
          ],
          "name": "Yafan Wang",
          "country": "CN"
        },
        {
          "is_winner": false,
          "set_games": [
            "7",
            "6",
            "3"
          ],
          "name": "Kristina Kucova",
          "country": "SK"
        }
      ],
      "duration": "03:20:10",
      "round": "Round of 32",
      "date": "2016-01-15"
    },
    {
      "players": [
        {
          "is_winner": false,
          "set_games": [
            "2",
            "1"
          ],
          "name": "Kailin Zhang",
          "country": "CN"
        },
        {
          "is_winner": true,
          "set_games": [
            "6",
            "6"
          ],
          "name": "Naomi Osaka",
          "country": "JP"
        }
      ],
      "duration": "01:01:13",
      "round": "Round of 32",
      "date": "2016-01-16"
    },
    {
      "players": [
        {
          "is_winner": true,
          "set_games": [
            "2",
            "6",
            "7"
          ],
          "name": "Kristyna Pliskova",
          "country": "CZ"
        },
        {
          "is_winner": false,
          "set_games": [
            "6",
            "2",
            "5"
          ],
          "name": "Sachia Vickery",
          "country": "US"
        }
      ],
      "duration": "01:42:25",
      "round": "Round of 32",
      "date": "2016-01-16"
    },
    {
      "players": [
        {
          "is_winner": true,
          "set_games": [
            "6",
            "6"
          ],
          "name": "Luksika Kumkhum",
          "country": "TH"
        },
        {
          "is_winner": false,
          "set_games": [
            "4",
            "2"
          ],
          "name": "Julia Glushko",
          "country": "IL"
        }
      ],
      "duration": "01:19:34",
      "round": "Round of 32",
      "date": "2016-01-16"
    }
  ],
  "players": [
    "Aleksandra Wozniak",
    "Alexa Glatch",
    "Alexandra Panova",
    "Alize Lim",
    "Alla Kudryavtseva",
    "Amandine Hesse",
    "An-Sophie Mestach",
    "Anastasija Sevastova",
    "Andrea Hlavackova",
    "Arina Rodionova",
    "Barbora Krejcikova",
    "Cagla Buyukakcay",
    "Cindy Burger",
    "Destanee Aiava",
    "Elena Vesnina",
    "Elise Mertens",
    "Eri Hozumi",
    "Fangzhou Liu",
    "Francesca Schiavone",
    "Heidi El Tabakh",
    "Hiroko Kuwata",
    "Ipek Soylu",
    "Irina Khromacheva",
    "Ivana Jorovic",
    "Jana Cepelova",
    "Jana Fett",
    "Jessica Pegula",
    "Jovana Jaksic",
    "Julia Boserup",
    "Julia Glushko",
    "Kai-Chen Chang",
    "Kailin Zhang",
    "Katerina Stewart",
    "Kateryna Kozlova",
    "Kimiko Date Krumm",
    "Kristie Ahn",
    "Kristina Kucova",
    "Kristyna Pliskova",
    "Laura Pous",
    "Lesley Kerkhove",
    "Lin Zhu",
    "Luksika Kumkhum",
    "Mandy Minella",
    "Marcela Zacarias",
    "Maria Irigoyen",
    "Maria Jose Martinez",
    "Maria Sakkari",
    "Maria Sanchez",
    "Maria Teresa Torro",
    "Marina Erakovic",
    "Maryna Zanevska",
    "Mathilde Johansson",
    "Mayo Hibi",
    "Michelle Larcher De Brito",
    "Misa Eguchi",
    "Miyu Kato",
    "Naiktha Bains",
    "Naomi Broady",
    "Naomi Osaka",
    "Nicole Gibbs",
    "Olga Savchuk",
    "Olivia Rogowska",
    "Olivia Tjandramulia",
    "Patricia Maria Tig",
    "Paula Kania",
    "Pauline Parmentier",
    "Petra Martic",
    "Qiang Wang",
    "Rebecca Peterson",
    "Richel Hogenkamp",
    "Risa Ozaki",
    "Sachia Vickery",
    "Sara Sorribes",
    "Sara Tomic",
    "Sesil Karatantcheva",
    "Shahar Peer",
    "Shuai Zhang",
    "Silvia Soler",
    "Stefanie Voegele",
    "Stephanie Foretz Gacon",
    "Stephanie Vogt",
    "Su-Jeong Jang",
    "Tamira Paszek",
    "Tereza Martincova",
    "Tereza Mihalikova",
    "Tereza Smitkova",
    "Vera Dushevina",
    "Veronica Cepede",
    "Viktorija Golubic",
    "Virginie Razzano",
    "Yafan Wang",
    "Yingying Duan",
    "Ysaline Bonaventure",
    "Yuxuan Zhang",
    "Zhaoxuan Yang",
    "Zoe Hives"
  ]
}